{"x":36,"z":148,"tiles":[{"x":53,"z":0,"level":0,"collision":16},{"x":53,"z":1,"level":0,"collision":16},{"x":53,"z":2,"level":0,"collision":16},{"x":53,"z":3,"level":0,"collision":16},{"x":53,"z":4,"level":0,"collision":16},{"x":53,"z":5,"level":0,"collision":16},{"x":53,"z":6,"level":0,"collision":16},{"x":53,"z":7,"level":0,"collision":16},{"x":53,"z":8,"level":0,"collision":16},{"x":54,"z":0,"level":0,"collision":16},{"x":54,"z":1,"level":0,"collision":16},{"x":54,"z":2,"level":0,"collision":16},{"x":54,"z":3,"level":0,"collision":16},{"x":54,"z":4,"level":0,"collision":16},{"x":54,"z":5,"level":0,"collision":16},{"x":54,"z":6,"level":0,"collision":16},{"x":54,"z":7,"level":0,"collision":16},{"x":54,"z":8,"level":0,"collision":16},{"x":55,"z":0,"level":0,"collision":16},{"x":55,"z":1,"level":0,"collision":16},{"x":55,"z":2,"level":0,"collision":16},{"x":55,"z":3,"level":0,"collision":16},{"x":55,"z":4,"level":0,"collision":16},{"x":55,"z":5,"level":0,"collision":16},{"x":55,"z":6,"level":0,"collision":16},{"x":55,"z":7,"level":0,"collision":16},{"x":55,"z":8,"level":0,"collision":16},{"x":56,"z":0,"level":0,"collision":16},{"x":56,"z":1,"level":0,"collision":16},{"x":56,"z":2,"level":0,"collision":16},{"x":56,"z":3,"level":0,"collision":16},{"x":56,"z":4,"level":0,"collision":16},{"x":56,"z":5,"level":0,"collision":16},{"x":56,"z":6,"level":0,"collision":16},{"x":56,"z":7,"level":0,"collision":16},{"x":56,"z":8,"level":0,"collision":16},{"x":57,"z":0,"level":0,"collision":16},{"x":57,"z":1,"level":0,"collision":16},{"x":57,"z":2,"level":0,"collision":16},{"x":57,"z":3,"level":0,"collision":16},{"x":57,"z":4,"level":0,"collision":16},{"x":57,"z":5,"level":0,"collision":16},{"x":57,"z":6,"level":0,"collision":16},{"x":57,"z":7,"level":0,"collision":16},{"x":57,"z":8,"level":0,"collision":16},{"x":58,"z":0,"level":0,"collision":16},{"x":58,"z":1,"level":0,"collision":16},{"x":58,"z":2,"level":0,"collision":16},{"x":58,"z":3,"level":0,"collision":16},{"x":58,"z":4,"level":0,"collision":16},{"x":58,"z":5,"level":0,"collision":16},{"x":58,"z":6,"level":0,"collision":16},{"x":58,"z":7,"level":0,"collision":16},{"x":58,"z":8,"level":0,"collision":16},{"x":59,"z":0,"level":0,"collision":16},{"x":59,"z":1,"level":0,"collision":16},{"x":59,"z":2,"level":0,"collision":16},{"x":59,"z":3,"level":0,"collision":16},{"x":59,"z":4,"level":0,"collision":16},{"x":59,"z":5,"level":0,"collision":16},{"x":59,"z":6,"level":0,"collision":16},{"x":59,"z":7,"level":0,"collision":16},{"x":59,"z":8,"level":0,"collision":16},{"x":60,"z":0,"level":0,"collision":16},{"x":60,"z":1,"level":0,"collision":16},{"x":60,"z":2,"level":0,"collision":16},{"x":60,"z":3,"level":0,"collision":16},{"x":60,"z":4,"level":0,"collision":16},{"x":60,"z":5,"level":0,"collision":16},{"x":60,"z":6,"level":0,"collision":16},{"x":60,"z":7,"level":0,"collision":16},{"x":60,"z":8,"level":0,"collision":16},{"x":61,"z":0,"level":0,"collision":16},{"x":61,"z":1,"level":0,"collision":16},{"x":61,"z":2,"level":0,"collision":16},{"x":61,"z":3,"level":0,"collision":16},{"x":61,"z":4,"level":0,"collision":16},{"x":61,"z":5,"level":0,"collision":16},{"x":61,"z":6,"level":0,"collision":16},{"x":61,"z":7,"level":0,"collision":16},{"x":61,"z":8,"level":0,"collision":16},{"x":62,"z":0,"level":0,"collision":16},{"x":62,"z":1,"level":0,"collision":16},{"x":62,"z":2,"level":0,"collision":16},{"x":62,"z":3,"level":0,"collision":16},{"x":62,"z":4,"level":0,"collision":16},{"x":62,"z":5,"level":0,"collision":16},{"x":62,"z":6,"level":0,"collision":16},{"x":62,"z":7,"level":0,"collision":16},{"x":62,"z":8,"level":0,"collision":16},{"x":63,"z":0,"level":0,"collision":16},{"x":63,"z":1,"level":0,"collision":16},{"x":63,"z":2,"level":0,"collision":16},{"x":63,"z":3,"level":0,"collision":16},{"x":63,"z":4,"level":0,"collision":16},{"x":63,"z":5,"level":0,"collision":16},{"x":63,"z":6,"level":0,"collision":16},{"x":63,"z":7,"level":0,"collision":16},{"x":63,"z":8,"level":0,"collision":16}],"locs":[{"x":53,"z":0,"level":0,"type":1434,"shape":10,"angle":0},{"x":53,"z":1,"level":0,"type":1434,"shape":10,"angle":0},{"x":53,"z":2,"level":0,"type":1434,"shape":10,"angle":0},{"x":53,"z":3,"level":0,"type":1434,"shape":10,"angle":0},{"x":53,"z":4,"level":0,"type":1434,"shape":10,"angle":0},{"x":53,"z":5,"level":0,"type":1434,"shape":10,"angle":0},{"x":53,"z":6,"level":0,"type":1434,"shape":10,"angle":0},{"x":53,"z":7,"level":0,"type":1434,"shape":10,"angle":0},{"x":53,"z":8,"level":0,"type":1434,"shape":10,"angle":0},{"x":54,"z":0,"level":0,"type":1434,"shape":10,"angle":0},{"x":54,"z":1,"level":0,"type":1434,"shape":10,"angle":0},{"x":54,"z":2,"level":0,"type":1434,"shape":10,"angle":0},{"x":54,"z":3,"level":0,"type":1434,"shape":10,"angle":0},{"x":54,"z":4,"level":0,"type":1434,"shape":10,"angle":0},{"x":54,"z":5,"level":0,"type":1434,"shape":10,"angle":0},{"x":54,"z":6,"level":0,"type":1434,"shape":10,"angle":0},{"x":54,"z":7,"level":0,"type":1434,"shape":10,"angle":0},{"x":54,"z":8,"level":0,"type":1434,"shape":10,"angle":0},{"x":55,"z":0,"level":0,"type":1434,"shape":10,"angle":0},{"x":55,"z":1,"level":0,"type":1434,"shape":10,"angle":0},{"x":55,"z":2,"level":0,"type":1434,"shape":10,"angle":0},{"x":55,"z":3,"level":0,"type":1434,"shape":10,"angle":0},{"x":55,"z":4,"level":0,"type":1434,"shape":10,"angle":0},{"x":55,"z":5,"level":0,"type":1434,"shape":10,"angle":0},{"x":55,"z":6,"level":0,"type":1434,"shape":10,"angle":0},{"x":55,"z":7,"level":0,"type":1434,"shape":10,"angle":0},{"x":55,"z":8,"level":0,"type":1434,"shape":10,"angle":0},{"x":56,"z":0,"level":0,"type":1434,"shape":10,"angle":0},{"x":56,"z":1,"level":0,"type":1434,"shape":10,"angle":0},{"x":56,"z":2,"level":0,"type":1434,"shape":10,"angle":0},{"x":56,"z":3,"level":0,"type":1434,"shape":10,"angle":0},{"x":56,"z":4,"level":0,"type":1434,"shape":10,"angle":0},{"x":56,"z":5,"level":0,"type":1434,"shape":10,"angle":0},{"x":56,"z":6,"level":0,"type":1434,"shape":10,"angle":0},{"x":56,"z":7,"level":0,"type":1434,"shape":10,"angle":0},{"x":56,"z":8,"level":0,"type":1434,"shape":10,"angle":0},{"x":57,"z":0,"level":0,"type":1434,"shape":10,"angle":0},{"x":57,"z":1,"level":0,"type":1434,"shape":10,"angle":0},{"x":57,"z":2,"level":0,"type":1434,"shape":10,"angle":0},{"x":57,"z":3,"level":0,"type":1434,"shape":10,"angle":0},{"x":57,"z":4,"level":0,"type":1434,"shape":10,"angle":0},{"x":57,"z":5,"level":0,"type":1434,"shape":10,"angle":0},{"x":57,"z":6,"level":0,"type":1434,"shape":10,"angle":0},{"x":57,"z":7,"level":0,"type":1434,"shape":10,"angle":0},{"x":57,"z":8,"level":0,"type":1434,"shape":10,"angle":0},{"x":58,"z":0,"level":0,"type":1434,"shape":10,"angle":0},{"x":58,"z":1,"level":0,"type":1434,"shape":10,"angle":0},{"x":58,"z":2,"level":0,"type":1434,"shape":10,"angle":0},{"x":58,"z":3,"level":0,"type":1434,"shape":10,"angle":0},{"x":58,"z":4,"level":0,"type":1434,"shape":10,"angle":0},{"x":58,"z":5,"level":0,"type":1434,"shape":10,"angle":0},{"x":58,"z":6,"level":0,"type":1434,"shape":10,"angle":0},{"x":58,"z":7,"level":0,"type":1434,"shape":10,"angle":0},{"x":58,"z":8,"level":0,"type":1434,"shape":10,"angle":0},{"x":59,"z":0,"level":0,"type":1434,"shape":10,"angle":0},{"x":59,"z":1,"level":0,"type":1434,"shape":10,"angle":0},{"x":59,"z":2,"level":0,"type":1434,"shape":10,"angle":0},{"x":59,"z":3,"level":0,"type":1434,"shape":10,"angle":0},{"x":59,"z":4,"level":0,"type":1434,"shape":10,"angle":0},{"x":59,"z":5,"level":0,"type":1434,"shape":10,"angle":0},{"x":59,"z":6,"level":0,"type":1434,"shape":10,"angle":0},{"x":59,"z":7,"level":0,"type":1434,"shape":10,"angle":0},{"x":59,"z":8,"level":0,"type":1434,"shape":10,"angle":0},{"x":60,"z":0,"level":0,"type":1434,"shape":10,"angle":0},{"x":60,"z":1,"level":0,"type":1434,"shape":10,"angle":0},{"x":60,"z":2,"level":0,"type":1434,"shape":10,"angle":0},{"x":60,"z":3,"level":0,"type":1434,"shape":10,"angle":0},{"x":60,"z":4,"level":0,"type":1434,"shape":10,"angle":0},{"x":60,"z":5,"level":0,"type":1434,"shape":10,"angle":0},{"x":60,"z":6,"level":0,"type":1434,"shape":10,"angle":0},{"x":60,"z":7,"level":0,"type":1434,"shape":10,"angle":0},{"x":60,"z":8,"level":0,"type":1434,"shape":10,"angle":0},{"x":61,"z":0,"level":0,"type":1434,"shape":10,"angle":0},{"x":61,"z":1,"level":0,"type":1434,"shape":10,"angle":0},{"x":61,"z":2,"level":0,"type":1434,"shape":10,"angle":0},{"x":61,"z":3,"level":0,"type":1434,"shape":10,"angle":0},{"x":61,"z":4,"level":0,"type":1434,"shape":10,"angle":0},{"x":61,"z":5,"level":0,"type":1434,"shape":10,"angle":0},{"x":61,"z":6,"level":0,"type":1434,"shape":10,"angle":0},{"x":61,"z":7,"level":0,"type":1434,"shape":10,"angle":0},{"x":61,"z":8,"level":0,"type":1434,"shape":10,"angle":0},{"x":62,"z":0,"level":0,"type":1434,"shape":10,"angle":0},{"x":62,"z":1,"level":0,"type":1434,"shape":10,"angle":0},{"x":62,"z":2,"level":0,"type":1434,"shape":10,"angle":0},{"x":62,"z":3,"level":0,"type":1434,"shape":10,"angle":0},{"x":62,"z":4,"level":0,"type":1434,"shape":10,"angle":0},{"x":62,"z":5,"level":0,"type":1434,"shape":10,"angle":0},{"x":62,"z":6,"level":0,"type":1434,"shape":10,"angle":0},{"x":62,"z":7,"level":0,"type":1434,"shape":10,"angle":0},{"x":62,"z":8,"level":0,"type":1434,"shape":10,"angle":0},{"x":63,"z":0,"level":0,"type":1434,"shape":10,"angle":0},{"x":63,"z":1,"level":0,"type":1434,"shape":10,"angle":0},{"x":63,"z":2,"level":0,"type":1434,"shape":10,"angle":0},{"x":63,"z":3,"level":0,"type":1434,"shape":10,"angle":0},{"x":63,"z":4,"level":0,"type":1434,"shape":10,"angle":0},{"x":63,"z":5,"level":0,"type":1434,"shape":10,"angle":0},{"x":63,"z":6,"level":0,"type":1434,"shape":10,"angle":0},{"x":63,"z":7,"level":0,"type":1434,"shape":10,"angle":0},{"x":63,"z":8,"level":0,"type":1434,"shape":10,"angle":0}],"npcs":[],"objs":[]}